taml/__init__.py
taml/main.py
taml/version.py
taml-1.1.0.dist-info/licenses/LICENSE
taml-1.1.0.dist-info/METADATA
taml-1.1.0.dist-info/WHEEL
taml-1.1.0.dist-info/top_level.txt
taml-1.1.0.dist-info/RECORD
